lsst/__init__.py
lsst/ctrl/__init__.py
lsst/ctrl/bps/__init__.py
lsst/ctrl/bps/_exceptions.py
lsst/ctrl/bps/bps_config.py
lsst/ctrl/bps/bps_draw.py
lsst/ctrl/bps/bps_reports.py
lsst/ctrl/bps/bps_utils.py
lsst/ctrl/bps/cancel.py
lsst/ctrl/bps/clustered_quantum_graph.py
lsst/ctrl/bps/constants.py
lsst/ctrl/bps/construct.py
lsst/ctrl/bps/drivers.py
lsst/ctrl/bps/generic_workflow.py
lsst/ctrl/bps/initialize.py
lsst/ctrl/bps/ping.py
lsst/ctrl/bps/pre_transform.py
lsst/ctrl/bps/prepare.py
lsst/ctrl/bps/quantum_clustering_funcs.py
lsst/ctrl/bps/report.py
lsst/ctrl/bps/restart.py
lsst/ctrl/bps/status.py
lsst/ctrl/bps/submit.py
lsst/ctrl/bps/transform.py
lsst/ctrl/bps/version.py
lsst/ctrl/bps/wms_service.py
lsst/ctrl/bps/cli/__init__.py
lsst/ctrl/bps/cli/bps.py
lsst/ctrl/bps/cli/cmd/__init__.py
lsst/ctrl/bps/cli/cmd/commands.py
lsst/ctrl/bps/cli/opt/__init__.py
lsst/ctrl/bps/cli/opt/arguments.py
lsst/ctrl/bps/cli/opt/option_groups.py
lsst/ctrl/bps/cli/opt/options.py
lsst/ctrl/bps/etc/bps_defaults.yaml
lsst/ctrl/bps/tests/config_test_utils.py
lsst/ctrl/bps/tests/gw_test_utils.py
lsst_ctrl_bps-30.2026.300.dist-info/licenses/COPYRIGHT
lsst_ctrl_bps-30.2026.300.dist-info/licenses/LICENSE
lsst_ctrl_bps-30.2026.300.dist-info/licenses/bsd_license.txt
lsst_ctrl_bps-30.2026.300.dist-info/licenses/gpl-v3.0.txt
lsst_ctrl_bps-30.2026.300.dist-info/METADATA
lsst_ctrl_bps-30.2026.300.dist-info/WHEEL
lsst_ctrl_bps-30.2026.300.dist-info/entry_points.txt
lsst_ctrl_bps-30.2026.300.dist-info/top_level.txt
lsst_ctrl_bps-30.2026.300.dist-info/zip-safe
lsst_ctrl_bps-30.2026.300.dist-info/RECORD
