Metadata-Version: 2.4
Name: lsst-ctrl-bps
Version: 30.2026.300
Summary: Pluggable execution of workflow graphs from Rubin pipelines.
Author-email: Rubin Observatory Data Management <dm-admin@lists.lsst.org>
License-Expression: BSD-3-Clause OR GPL-3.0-or-later
Project-URL: Homepage, https://github.com/lsst/ctrl_bps
Keywords: lsst
Classifier: Intended Audience :: Science/Research
Classifier: Operating System :: OS Independent
Classifier: Programming Language :: Python :: 3
Classifier: Programming Language :: Python :: 3.11
Classifier: Programming Language :: Python :: 3.12
Classifier: Programming Language :: Python :: 3.13
Classifier: Programming Language :: Python :: 3.14
Classifier: Topic :: Scientific/Engineering :: Astronomy
Requires-Python: >=3.11.0
License-File: COPYRIGHT
License-File: LICENSE
License-File: bsd_license.txt
License-File: gpl-v3.0.txt
Requires-Dist: astropy>=4.0
Requires-Dist: pyyaml>=5.1
Requires-Dist: click>=7.0
Requires-Dist: networkx
Requires-Dist: lsst-daf-butler
Requires-Dist: lsst-pipe-base
Requires-Dist: lsst-ctrl-mpexec
Requires-Dist: lsst-utils
Requires-Dist: lsst-resources
Provides-Extra: test
Requires-Dist: pytest>=3.2; extra == "test"
Requires-Dist: pytest-openfiles>=0.5.0; extra == "test"
Dynamic: license-file
